MANIFEST.in
README.rst
readme.md
readme.rst
setup.py
macho_analysis/__init__.py
macho_analysis.egg-info/PKG-INFO
macho_analysis.egg-info/SOURCES.txt
macho_analysis.egg-info/dependency_links.txt
macho_analysis.egg-info/not-zip-safe
macho_analysis.egg-info/top_level.txt
macho_analysis/utils/__init__.py
macho_analysis/utils/find_dependency.py
macho_analysis/utils/find_symbol.py