Metadata-Version: 1.1
Name: macho-analysis
Version: 0.011
Summary: some utils to help analysis macho files,include util to find which module call the symbol and the dependencies between the modules
Home-page: UNKNOWN
Author: chaoran zhang
Author-email: en756303625@163.com
License: MIT
Platform: UNKNOWN
Classifier: Development Status :: 3 - Alpha
Classifier: License :: OSI Approved :: MIT License
Classifier: Programming Language :: Python :: 2.7
